pylnk3.py
pylnk3-0.4.2.dist-info/LICENSE
pylnk3-0.4.2.dist-info/METADATA
pylnk3-0.4.2.dist-info/WHEEL
pylnk3-0.4.2.dist-info/entry_points.txt
pylnk3-0.4.2.dist-info/top_level.txt
pylnk3-0.4.2.dist-info/RECORD
