Metadata-Version: 2.1
Name: pylnk3
Version: 0.4.2
Summary: Windows LNK File Parser and Creator
Home-page: https://github.com/strayge/pylnk
Author: strayge
Author-email: strayge@gmail.com
License: GNU Library or Lesser General Public License (LGPL)
Keywords: lnk,shortcut,windows
Platform: UNKNOWN
Classifier: Programming Language :: Python :: 3.6
Classifier: Programming Language :: Python :: 3.7
Classifier: Programming Language :: Python :: 3.8
Classifier: Programming Language :: Python :: 3.9
Classifier: Intended Audience :: Developers
Classifier: License :: OSI Approved :: GNU Library or Lesser General Public License (LGPL)
Classifier: Operating System :: OS Independent
Classifier: Topic :: Software Development :: Libraries :: Python Modules
Requires-Python: >=3.6
